<?xml version="1.0" encoding="UTF-8" standalone="yes"?>
<w:document xmlns:wpc="http://schemas.microsoft.com/office/word/2010/wordprocessingCanvas" xmlns:cx="http://schemas.microsoft.com/office/drawing/2014/chartex" xmlns:cx1="http://schemas.microsoft.com/office/drawing/2015/9/8/chartex" xmlns:cx2="http://schemas.microsoft.com/office/drawing/2015/10/21/chartex" xmlns:cx3="http://schemas.microsoft.com/office/drawing/2016/5/9/chartex" xmlns:cx4="http://schemas.microsoft.com/office/drawing/2016/5/10/chartex" xmlns:cx5="http://schemas.microsoft.com/office/drawing/2016/5/11/chartex" xmlns:cx6="http://schemas.microsoft.com/office/drawing/2016/5/12/chartex" xmlns:cx7="http://schemas.microsoft.com/office/drawing/2016/5/13/chartex" xmlns:cx8="http://schemas.microsoft.com/office/drawing/2016/5/14/chartex" xmlns:mc="http://schemas.openxmlformats.org/markup-compatibility/2006" xmlns:aink="http://schemas.microsoft.com/office/drawing/2016/ink" xmlns:am3d="http://schemas.microsoft.com/office/drawing/2017/model3d" xmlns:o="urn:schemas-microsoft-com:office:office" xmlns:oel="http://schemas.microsoft.com/office/2019/extlst" xmlns:r="http://schemas.openxmlformats.org/officeDocument/2006/relationships" xmlns:m="http://schemas.openxmlformats.org/officeDocument/2006/math" xmlns:v="urn:schemas-microsoft-com:vml" xmlns:wp14="http://schemas.microsoft.com/office/word/2010/wordprocessingDrawing" xmlns:wp="http://schemas.openxmlformats.org/drawingml/2006/wordprocessingDrawing" xmlns:w10="urn:schemas-microsoft-com:office:word" xmlns:w="http://schemas.openxmlformats.org/wordprocessingml/2006/main" xmlns:w14="http://schemas.microsoft.com/office/word/2010/wordml" xmlns:w15="http://schemas.microsoft.com/office/word/2012/wordml" xmlns:w16cex="http://schemas.microsoft.com/office/word/2018/wordml/cex" xmlns:w16cid="http://schemas.microsoft.com/office/word/2016/wordml/cid" xmlns:w16="http://schemas.microsoft.com/office/word/2018/wordml" xmlns:w16du="http://schemas.microsoft.com/office/word/2023/wordml/word16du" xmlns:w16sdtdh="http://schemas.microsoft.com/office/word/2020/wordml/sdtdatahash" xmlns:w16sdtfl="http://schemas.microsoft.com/office/word/2024/wordml/sdtformatlock" xmlns:w16se="http://schemas.microsoft.com/office/word/2015/wordml/symex" xmlns:wpg="http://schemas.microsoft.com/office/word/2010/wordprocessingGroup" xmlns:wpi="http://schemas.microsoft.com/office/word/2010/wordprocessingInk" xmlns:wne="http://schemas.microsoft.com/office/word/2006/wordml" xmlns:wps="http://schemas.microsoft.com/office/word/2010/wordprocessingShape" mc:Ignorable="w14 w15 w16se w16cid w16 w16cex w16sdtdh w16sdtfl w16du wp14"><w:body><w:p w14:paraId="00D5418A" w14:textId="2B906A69" w:rsidR="009E336D" w:rsidRDefault="00B95E91" w:rsidP="00DD6A89"><w:pPr><w:jc w:val="center"/><w:rPr><w:b/><w:bCs/><w:sz w:val="24"/><w:szCs w:val="24"/></w:rPr></w:pPr><w:proofErr w:type="spellStart"/><w:r w:rsidRPr="00DD6A89"><w:rPr><w:b/><w:bCs/><w:sz w:val="24"/><w:szCs w:val="24"/></w:rPr><w:t>Flobitz</w:t></w:r><w:proofErr w:type="spellEnd"/><w:r w:rsidRPr="00DD6A89"><w:rPr><w:b/><w:bCs/><w:sz w:val="24"/><w:szCs w:val="24"/></w:rPr><w:t xml:space="preserve"> Home Page (Landing Page Structure)</w:t></w:r></w:p><w:p w14:paraId="1A525BFD" w14:textId="77777777" w:rsidR="00DD6A89" w:rsidRPr="00DD6A89" w:rsidRDefault="00DD6A89" w:rsidP="00DD6A89"><w:pPr><w:jc w:val="center"/><w:rPr><w:b/><w:bCs/><w:sz w:val="24"/><w:szCs w:val="24"/></w:rPr></w:pPr></w:p><w:p w14:paraId="40FC5688" w14:textId="77777777" w:rsidR="00DD6A89" w:rsidRPr="00B95E91" w:rsidRDefault="00DD6A89"><w:pPr><w:rPr><w:b/><w:bCs/><w:sz w:val="24"/><w:szCs w:val="24"/></w:rPr></w:pPr></w:p><w:p w14:paraId="69743D43" w14:textId="7B94E49B" w:rsidR="00B95E91" w:rsidRDefault="00B95E91"><w:pPr><w:rPr><w:b/><w:bCs/></w:rPr></w:pPr><w:r w:rsidRPr="00B95E91"><w:rPr><w:b/><w:bCs/></w:rPr><w:t>(Top Banner)</w:t></w:r></w:p><w:p w14:paraId="2EBB5C0B" w14:textId="77777777" w:rsidR="00B95E91" w:rsidRPr="00B95E91" w:rsidRDefault="00B95E91" w:rsidP="00B95E91"><w:r w:rsidRPr="00B95E91"><w:t>This is the first thing users see</w:t></w:r></w:p><w:p w14:paraId="64C6DBCC" w14:textId="77777777" w:rsidR="00B95E91" w:rsidRPr="00B95E91" w:rsidRDefault="00B95E91" w:rsidP="00B95E91"><w:pPr><w:rPr><w:u w:val="single"/></w:rPr></w:pPr><w:r w:rsidRPr="00B95E91"><w:rPr><w:u w:val="single"/></w:rPr><w:t>Headline:</w:t></w:r></w:p><w:p w14:paraId="3BEB1E17" w14:textId="77777777" w:rsidR="00B95E91" w:rsidRPr="00B95E91" w:rsidRDefault="00B95E91" w:rsidP="00B95E91"><w:pPr><w:ind w:firstLine="720"/></w:pPr><w:r w:rsidRPr="00B95E91"><w:rPr><w:i/><w:iCs/></w:rPr><w:t>Empowering Businesses with Smart IT, Financial &amp; Creative Solutions</w:t></w:r></w:p><w:p w14:paraId="45EE314C" w14:textId="77777777" w:rsidR="00B95E91" w:rsidRPr="00B95E91" w:rsidRDefault="00B95E91" w:rsidP="00B95E91"><w:pPr><w:rPr><w:u w:val="single"/></w:rPr></w:pPr><w:r w:rsidRPr="00B95E91"><w:rPr><w:u w:val="single"/></w:rPr><w:t>Subtext:</w:t></w:r></w:p><w:p w14:paraId="5DE5FB63" w14:textId="77777777" w:rsidR="00B95E91" w:rsidRPr="00B95E91" w:rsidRDefault="00B95E91" w:rsidP="00B95E91"><w:pPr><w:ind w:firstLine="720"/></w:pPr><w:r w:rsidRPr="00B95E91"><w:t xml:space="preserve">At </w:t></w:r><w:proofErr w:type="spellStart"/><w:r w:rsidRPr="00B95E91"><w:t>Flobitz</w:t></w:r><w:proofErr w:type="spellEnd"/><w:r w:rsidRPr="00B95E91"><w:t>, we combine technology, finance, and design to help businesses grow faster, smarter, and stronger.</w:t></w:r></w:p><w:p w14:paraId="5AE9E971" w14:textId="77777777" w:rsidR="00B95E91" w:rsidRPr="00B95E91" w:rsidRDefault="00B95E91" w:rsidP="00B95E91"><w:pPr><w:rPr><w:u w:val="single"/></w:rPr></w:pPr><w:r w:rsidRPr="00B95E91"><w:rPr><w:u w:val="single"/></w:rPr><w:t>Buttons:</w:t></w:r></w:p><w:p w14:paraId="5AAD8424" w14:textId="77777777" w:rsidR="00B95E91" w:rsidRPr="00B95E91" w:rsidRDefault="00B95E91" w:rsidP="00B95E91"><w:pPr><w:numPr><w:ilvl w:val="0"/><w:numId w:val="1"/></w:numPr></w:pPr><w:r w:rsidRPr="00B95E91"><w:t xml:space="preserve">Get Started </w:t></w:r></w:p><w:p w14:paraId="4DB34F17" w14:textId="77777777" w:rsidR="00B95E91" w:rsidRDefault="00B95E91" w:rsidP="00B95E91"><w:pPr><w:numPr><w:ilvl w:val="0"/><w:numId w:val="1"/></w:numPr></w:pPr><w:r w:rsidRPr="00B95E91"><w:t>Contact Us</w:t></w:r></w:p><w:p w14:paraId="5C5D197A" w14:textId="77777777" w:rsidR="00B95E91" w:rsidRDefault="00B95E91" w:rsidP="00B95E91"/><w:p w14:paraId="7B6F17E6" w14:textId="77777777" w:rsidR="00B95E91" w:rsidRDefault="00B95E91" w:rsidP="00B95E91"/><w:p w14:paraId="1FBBDD6A" w14:textId="1976CBA3" w:rsidR="00B95E91" w:rsidRPr="00B95E91" w:rsidRDefault="00B95E91" w:rsidP="00B95E91"><w:pPr><w:rPr><w:sz w:val="24"/><w:szCs w:val="24"/></w:rPr></w:pPr><w:r w:rsidRPr="00B95E91"><w:rPr><w:b/><w:bCs/><w:sz w:val="24"/><w:szCs w:val="24"/></w:rPr><w:t xml:space="preserve">About </w:t></w:r><w:proofErr w:type="spellStart"/><w:r w:rsidRPr="00B95E91"><w:rPr><w:b/><w:bCs/><w:sz w:val="24"/><w:szCs w:val="24"/></w:rPr><w:t>Flobitz</w:t></w:r><w:proofErr w:type="spellEnd"/><w:r w:rsidRPr="00B95E91"><w:rPr><w:b/><w:bCs/><w:sz w:val="24"/><w:szCs w:val="24"/></w:rPr><w:t xml:space="preserve"> (Brief Intro)</w:t></w:r></w:p><w:p w14:paraId="5757D18C" w14:textId="77777777" w:rsidR="006C635A" w:rsidRPr="006C635A" w:rsidRDefault="006C635A" w:rsidP="006C635A"><w:pPr><w:rPr><w:sz w:val="24"/><w:szCs w:val="24"/></w:rPr></w:pPr><w:proofErr w:type="spellStart"/><w:r w:rsidRPr="006C635A"><w:rPr><w:sz w:val="24"/><w:szCs w:val="24"/></w:rPr><w:t>Flobitz</w:t></w:r><w:proofErr w:type="spellEnd"/><w:r w:rsidRPr="006C635A"><w:rPr><w:sz w:val="24"/><w:szCs w:val="24"/></w:rPr><w:t xml:space="preserve"> is a dynamic and forward-thinking company delivering high-quality IT, financial, and graphic design solutions to businesses of all sizes. With over </w:t></w:r><w:r w:rsidRPr="006C635A"><w:rPr><w:b/><w:bCs/><w:sz w:val="24"/><w:szCs w:val="24"/></w:rPr><w:t>3+ years of industry experience</w:t></w:r><w:r w:rsidRPr="006C635A"><w:rPr><w:sz w:val="24"/><w:szCs w:val="24"/></w:rPr><w:t>, we have built a strong foundation of trust, innovation, and excellence.</w:t></w:r></w:p><w:p w14:paraId="5F0ECF7C" w14:textId="77777777" w:rsidR="006C635A" w:rsidRPr="006C635A" w:rsidRDefault="006C635A" w:rsidP="006C635A"><w:pPr><w:rPr><w:sz w:val="24"/><w:szCs w:val="24"/></w:rPr></w:pPr><w:r w:rsidRPr="006C635A"><w:rPr><w:sz w:val="24"/><w:szCs w:val="24"/></w:rPr><w:t xml:space="preserve">Our team consists of </w:t></w:r><w:r w:rsidRPr="006C635A"><w:rPr><w:b/><w:bCs/><w:sz w:val="24"/><w:szCs w:val="24"/></w:rPr><w:t>multi-talented professionals</w:t></w:r><w:r w:rsidRPr="006C635A"><w:rPr><w:sz w:val="24"/><w:szCs w:val="24"/></w:rPr><w:t xml:space="preserve"> specializing in technology, finance, and creative design. We work collaboratively to provide smart, efficient, and customized solutions tailored to each client’s needs.</w:t></w:r></w:p><w:p w14:paraId="563AA9E7" w14:textId="63032472" w:rsidR="006C635A" w:rsidRPr="006C635A" w:rsidRDefault="006C635A" w:rsidP="006C635A"><w:pPr><w:rPr><w:sz w:val="24"/><w:szCs w:val="24"/></w:rPr></w:pPr><w:r w:rsidRPr="006C635A"><w:rPr><w:sz w:val="24"/><w:szCs w:val="24"/></w:rPr><w:t xml:space="preserve">Over the years, we have successfully completed </w:t></w:r><w:r w:rsidR="00433465"><w:rPr><w:b/><w:bCs/><w:sz w:val="24"/><w:szCs w:val="24"/></w:rPr><w:t>50</w:t></w:r><w:r w:rsidRPr="006C635A"><w:rPr><w:b/><w:bCs/><w:sz w:val="24"/><w:szCs w:val="24"/></w:rPr><w:t>+ projects</w:t></w:r><w:r w:rsidRPr="006C635A"><w:rPr><w:sz w:val="24"/><w:szCs w:val="24"/></w:rPr><w:t xml:space="preserve"> for clients across various industries, helping them improve performance, strengthen their digital presence, and achieve their business goals. Currently, we are actively working on </w:t></w:r><w:r w:rsidR="00433465"><w:rPr><w:b/><w:bCs/><w:sz w:val="24"/><w:szCs w:val="24"/></w:rPr><w:t xml:space="preserve">15+ </w:t></w:r><w:r w:rsidRPr="006C635A"><w:rPr><w:b/><w:bCs/><w:sz w:val="24"/><w:szCs w:val="24"/></w:rPr><w:t>ongoing projects</w:t></w:r><w:r w:rsidRPr="006C635A"><w:rPr><w:sz w:val="24"/><w:szCs w:val="24"/></w:rPr><w:t>, ensuring continuous growth and long-term partnerships.</w:t></w:r></w:p><w:p w14:paraId="2394E54D" w14:textId="77777777" w:rsidR="006C635A" w:rsidRPr="006C635A" w:rsidRDefault="006C635A" w:rsidP="006C635A"><w:pPr><w:rPr><w:sz w:val="24"/><w:szCs w:val="24"/></w:rPr></w:pPr><w:r w:rsidRPr="006C635A"><w:rPr><w:sz w:val="24"/><w:szCs w:val="24"/></w:rPr><w:t xml:space="preserve">At </w:t></w:r><w:proofErr w:type="spellStart"/><w:r w:rsidRPr="006C635A"><w:rPr><w:sz w:val="24"/><w:szCs w:val="24"/></w:rPr><w:t>Flobitz</w:t></w:r><w:proofErr w:type="spellEnd"/><w:r w:rsidRPr="006C635A"><w:rPr><w:sz w:val="24"/><w:szCs w:val="24"/></w:rPr><w:t xml:space="preserve">, we believe in delivering not just services, but </w:t></w:r><w:r w:rsidRPr="006C635A"><w:rPr><w:b/><w:bCs/><w:sz w:val="24"/><w:szCs w:val="24"/></w:rPr><w:t>value and results</w:t></w:r><w:r w:rsidRPr="006C635A"><w:rPr><w:sz w:val="24"/><w:szCs w:val="24"/></w:rPr><w:t>. Our commitment to quality, transparency, and client satisfaction makes us a trusted partner for businesses looking to grow and succeed in today’s competitive market.</w:t></w:r></w:p><w:p w14:paraId="3CF52CD7" w14:textId="77777777" w:rsidR="0039755C" w:rsidRDefault="0039755C" w:rsidP="00B95E91"><w:pPr><w:rPr><w:sz w:val="24"/><w:szCs w:val="24"/></w:rPr></w:pPr></w:p><w:p w14:paraId="4E0C6D8B" w14:textId="77777777" w:rsidR="00DD6A89" w:rsidRDefault="00DD6A89" w:rsidP="00B95E91"><w:pPr><w:rPr><w:sz w:val="24"/><w:szCs w:val="24"/></w:rPr></w:pPr></w:p><w:p w14:paraId="5CD21FC0" w14:textId="77777777" w:rsidR="00B95E91" w:rsidRDefault="00B95E91" w:rsidP="00B95E91"><w:pPr><w:rPr><w:sz w:val="24"/><w:szCs w:val="24"/></w:rPr></w:pPr></w:p><w:p w14:paraId="4E6B1678" w14:textId="098CDEDB" w:rsidR="00B95E91" w:rsidRPr="00B95E91" w:rsidRDefault="00B95E91" w:rsidP="00B95E91"><w:pPr><w:rPr><w:b/><w:bCs/><w:sz w:val="24"/><w:szCs w:val="24"/></w:rPr></w:pPr><w:r w:rsidRPr="00B95E91"><w:rPr><w:b/><w:bCs/><w:sz w:val="24"/><w:szCs w:val="24"/></w:rPr><w:t>Our Services</w:t></w:r></w:p><w:p w14:paraId="156C41D0" w14:textId="77777777" w:rsidR="00B95E91" w:rsidRPr="00B95E91" w:rsidRDefault="00B95E91" w:rsidP="00B95E91"><w:pPr><w:rPr><w:b/><w:bCs/><w:sz w:val="24"/><w:szCs w:val="24"/><w:u w:val="single"/></w:rPr></w:pPr><w:r w:rsidRPr="00B95E91"><w:rPr><w:b/><w:bCs/><w:sz w:val="24"/><w:szCs w:val="24"/><w:u w:val="single"/></w:rPr><w:lastRenderedPageBreak/><w:t>IT Services</w:t></w:r></w:p><w:p w14:paraId="752575F7" w14:textId="2D42351D" w:rsidR="00B95E91" w:rsidRPr="00B95E91" w:rsidRDefault="00B95E91" w:rsidP="00B95E91"><w:pPr><w:rPr><w:sz w:val="24"/><w:szCs w:val="24"/></w:rPr></w:pPr><w:r w:rsidRPr="00B95E91"><w:rPr><w:sz w:val="24"/><w:szCs w:val="24"/></w:rPr><w:t>Custom, web development, cloud solutions</w:t></w:r><w:r><w:rPr><w:sz w:val="24"/><w:szCs w:val="24"/></w:rPr><w:t xml:space="preserve"> , Ai chat bot , </w:t></w:r><w:r w:rsidRPr="00B95E91"><w:rPr><w:sz w:val="24"/><w:szCs w:val="24"/></w:rPr><w:t>to power your business digitally.</w:t></w:r></w:p><w:p w14:paraId="392B87C8" w14:textId="0C09F5FE" w:rsidR="00B95E91" w:rsidRPr="00B95E91" w:rsidRDefault="00B95E91" w:rsidP="00B95E91"><w:pPr><w:rPr><w:b/><w:bCs/><w:sz w:val="24"/><w:szCs w:val="24"/><w:u w:val="single"/></w:rPr></w:pPr><w:r w:rsidRPr="00B95E91"><w:rPr><w:b/><w:bCs/><w:sz w:val="24"/><w:szCs w:val="24"/><w:u w:val="single"/></w:rPr><w:t xml:space="preserve"> Financial Services</w:t></w:r></w:p><w:p w14:paraId="1A845C06" w14:textId="183DF8BA" w:rsidR="00B95E91" w:rsidRDefault="00B95E91" w:rsidP="00B95E91"><w:pPr><w:rPr><w:sz w:val="24"/><w:szCs w:val="24"/></w:rPr></w:pPr><w:r><w:rPr><w:sz w:val="24"/><w:szCs w:val="24"/></w:rPr><w:t xml:space="preserve">Accounting and </w:t></w:r><w:proofErr w:type="spellStart"/><w:r><w:rPr><w:sz w:val="24"/><w:szCs w:val="24"/></w:rPr><w:t>Bookepping</w:t></w:r><w:proofErr w:type="spellEnd"/><w:r><w:rPr><w:sz w:val="24"/><w:szCs w:val="24"/></w:rPr><w:t xml:space="preserve">, VAT registration &amp; deregistration, Corporate Tax registration , VAT Filling </w:t></w:r><w:r w:rsidRPr="00B95E91"><w:rPr><w:sz w:val="24"/><w:szCs w:val="24"/></w:rPr><w:t>.</w:t></w:r></w:p><w:p w14:paraId="11EBF73F" w14:textId="2156D05E" w:rsidR="00B95E91" w:rsidRPr="00B95E91" w:rsidRDefault="00B95E91" w:rsidP="00B95E91"><w:pPr><w:rPr><w:sz w:val="24"/><w:szCs w:val="24"/><w:u w:val="single"/></w:rPr></w:pPr><w:r w:rsidRPr="00B95E91"><w:rPr><w:b/><w:bCs/><w:sz w:val="24"/><w:szCs w:val="24"/><w:u w:val="single"/></w:rPr><w:t>Graphic Designing</w:t></w:r></w:p><w:p w14:paraId="2478DDDE" w14:textId="5E07B733" w:rsidR="00B95E91" w:rsidRPr="00DD6A89" w:rsidRDefault="00B95E91" w:rsidP="00B95E91"><w:pPr><w:rPr><w:b/><w:bCs/><w:sz w:val="24"/><w:szCs w:val="24"/></w:rPr></w:pPr><w:r w:rsidRPr="00B95E91"><w:rPr><w:sz w:val="24"/><w:szCs w:val="24"/></w:rPr><w:t xml:space="preserve">Creative branding, </w:t></w:r><w:r><w:rPr><w:sz w:val="24"/><w:szCs w:val="24"/></w:rPr><w:t xml:space="preserve">Logo </w:t></w:r><w:r w:rsidRPr="00B95E91"><w:rPr><w:sz w:val="24"/><w:szCs w:val="24"/></w:rPr><w:t>design,</w:t></w:r><w:r><w:rPr><w:sz w:val="24"/><w:szCs w:val="24"/></w:rPr><w:t xml:space="preserve"> video editing , </w:t></w:r><w:r w:rsidRPr="00B95E91"><w:rPr><w:sz w:val="24"/><w:szCs w:val="24"/></w:rPr><w:t>visual content</w:t></w:r><w:r><w:rPr><w:sz w:val="24"/><w:szCs w:val="24"/></w:rPr><w:t xml:space="preserve"> and Social media handling  </w:t></w:r><w:r w:rsidRPr="00B95E91"><w:rPr><w:sz w:val="24"/><w:szCs w:val="24"/></w:rPr><w:t xml:space="preserve"> that makes your business stand out.</w:t></w:r></w:p><w:p w14:paraId="0EABF752" w14:textId="2611EF9E" w:rsidR="00B95E91" w:rsidRPr="00DD6A89" w:rsidRDefault="00DD6A89" w:rsidP="00B95E91"><w:pPr><w:rPr><w:b/><w:bCs/><w:u w:val="single"/></w:rPr></w:pPr><w:r w:rsidRPr="00DD6A89"><w:rPr><w:b/><w:bCs/><w:sz w:val="24"/><w:szCs w:val="24"/><w:u w:val="single"/></w:rPr><w:t xml:space="preserve">Why Choose </w:t></w:r><w:proofErr w:type="spellStart"/><w:r w:rsidRPr="00DD6A89"><w:rPr><w:b/><w:bCs/><w:sz w:val="24"/><w:szCs w:val="24"/><w:u w:val="single"/></w:rPr><w:t>Flobitz</w:t></w:r><w:proofErr w:type="spellEnd"/></w:p><w:p w14:paraId="3F4C82D8" w14:textId="77777777" w:rsidR="00DD6A89" w:rsidRPr="00DD6A89" w:rsidRDefault="00DD6A89" w:rsidP="00DD6A89"><w:pPr><w:numPr><w:ilvl w:val="0"/><w:numId w:val="2"/></w:numPr><w:rPr><w:b/><w:bCs/></w:rPr></w:pPr><w:r w:rsidRPr="00DD6A89"><w:rPr><w:rFonts w:ascii="Segoe UI Symbol" w:hAnsi="Segoe UI Symbol" w:cs="Segoe UI Symbol"/><w:b/><w:bCs/></w:rPr><w:t>✔</w:t></w:r><w:r w:rsidRPr="00DD6A89"><w:rPr><w:b/><w:bCs/></w:rPr><w:t xml:space="preserve"> Expert Team </w:t></w:r></w:p><w:p w14:paraId="75447527" w14:textId="77777777" w:rsidR="00DD6A89" w:rsidRPr="00DD6A89" w:rsidRDefault="00DD6A89" w:rsidP="00DD6A89"><w:pPr><w:numPr><w:ilvl w:val="0"/><w:numId w:val="2"/></w:numPr><w:rPr><w:b/><w:bCs/></w:rPr></w:pPr><w:r w:rsidRPr="00DD6A89"><w:rPr><w:rFonts w:ascii="Segoe UI Symbol" w:hAnsi="Segoe UI Symbol" w:cs="Segoe UI Symbol"/><w:b/><w:bCs/></w:rPr><w:t>✔</w:t></w:r><w:r w:rsidRPr="00DD6A89"><w:rPr><w:b/><w:bCs/></w:rPr><w:t xml:space="preserve"> Innovative Solutions </w:t></w:r></w:p><w:p w14:paraId="5E4F4D75" w14:textId="77777777" w:rsidR="00DD6A89" w:rsidRPr="00DD6A89" w:rsidRDefault="00DD6A89" w:rsidP="00DD6A89"><w:pPr><w:numPr><w:ilvl w:val="0"/><w:numId w:val="2"/></w:numPr><w:rPr><w:b/><w:bCs/></w:rPr></w:pPr><w:r w:rsidRPr="00DD6A89"><w:rPr><w:rFonts w:ascii="Segoe UI Symbol" w:hAnsi="Segoe UI Symbol" w:cs="Segoe UI Symbol"/><w:b/><w:bCs/></w:rPr><w:t>✔</w:t></w:r><w:r w:rsidRPr="00DD6A89"><w:rPr><w:b/><w:bCs/></w:rPr><w:t xml:space="preserve"> Client-Centric Approach </w:t></w:r></w:p><w:p w14:paraId="235B57C0" w14:textId="77777777" w:rsidR="00DD6A89" w:rsidRPr="00DD6A89" w:rsidRDefault="00DD6A89" w:rsidP="00DD6A89"><w:pPr><w:numPr><w:ilvl w:val="0"/><w:numId w:val="2"/></w:numPr><w:rPr><w:b/><w:bCs/></w:rPr></w:pPr><w:r w:rsidRPr="00DD6A89"><w:rPr><w:rFonts w:ascii="Segoe UI Symbol" w:hAnsi="Segoe UI Symbol" w:cs="Segoe UI Symbol"/><w:b/><w:bCs/></w:rPr><w:t>✔</w:t></w:r><w:r w:rsidRPr="00DD6A89"><w:rPr><w:b/><w:bCs/></w:rPr><w:t xml:space="preserve"> Affordable Pricing </w:t></w:r></w:p><w:p w14:paraId="4FB1AE0D" w14:textId="20A696E7" w:rsidR="00B95E91" w:rsidRDefault="00DD6A89" w:rsidP="00B95E91"><w:pPr><w:numPr><w:ilvl w:val="0"/><w:numId w:val="2"/></w:numPr><w:rPr><w:b/><w:bCs/><w:sz w:val="24"/><w:szCs w:val="24"/></w:rPr></w:pPr><w:r w:rsidRPr="00DD6A89"><w:rPr><w:rFonts w:ascii="Segoe UI Symbol" w:hAnsi="Segoe UI Symbol" w:cs="Segoe UI Symbol"/><w:b/><w:bCs/></w:rPr><w:t>✔</w:t></w:r><w:r w:rsidRPr="00DD6A89"><w:rPr><w:b/><w:bCs/></w:rPr><w:t xml:space="preserve"> End-to-End Services</w:t></w:r><w:r w:rsidRPr="00DD6A89"><w:rPr><w:b/><w:bCs/><w:sz w:val="24"/><w:szCs w:val="24"/></w:rPr><w:t xml:space="preserve"> </w:t></w:r></w:p><w:p w14:paraId="0ED2D9B7" w14:textId="77777777" w:rsidR="00DD6A89" w:rsidRDefault="00DD6A89" w:rsidP="00DD6A89"><w:pPr><w:rPr><w:b/><w:bCs/><w:sz w:val="24"/><w:szCs w:val="24"/></w:rPr></w:pPr></w:p><w:p w14:paraId="4C61CD8C" w14:textId="1EBEA6E9" w:rsidR="00DD6A89" w:rsidRPr="00DD6A89" w:rsidRDefault="00DD6A89" w:rsidP="00DD6A89"><w:pPr><w:rPr><w:b/><w:bCs/><w:sz w:val="24"/><w:szCs w:val="24"/><w:u w:val="single"/></w:rPr></w:pPr><w:r w:rsidRPr="00DD6A89"><w:rPr><w:b/><w:bCs/><w:sz w:val="24"/><w:szCs w:val="24"/><w:u w:val="single"/></w:rPr><w:t>Our Process</w:t></w:r></w:p><w:p w14:paraId="65DCF3E0" w14:textId="77777777" w:rsidR="00DD6A89" w:rsidRPr="00DD6A89" w:rsidRDefault="00DD6A89" w:rsidP="00DD6A89"><w:r w:rsidRPr="00DD6A89"><w:t>Understand → Plan → Execute → Deliver</w:t></w:r></w:p><w:p w14:paraId="4ADD1E4B" w14:textId="77777777" w:rsidR="00DD6A89" w:rsidRPr="00DD6A89" w:rsidRDefault="00DD6A89" w:rsidP="00DD6A89"><w:r w:rsidRPr="00DD6A89"><w:t>We follow a structured approach to ensure quality, efficiency, and client satisfaction.</w:t></w:r></w:p><w:p w14:paraId="2284C827" w14:textId="77777777" w:rsidR="00DD6A89" w:rsidRPr="00DD6A89" w:rsidRDefault="00DD6A89" w:rsidP="00DD6A89"><w:pPr><w:rPr><w:b/><w:bCs/><w:sz w:val="24"/><w:szCs w:val="24"/><w:u w:val="single"/></w:rPr></w:pPr></w:p><w:p w14:paraId="72425D4A" w14:textId="3ECE85C8" w:rsidR="00DD6A89" w:rsidRPr="00DD6A89" w:rsidRDefault="00DD6A89" w:rsidP="00DD6A89"><w:pPr><w:rPr><w:b/><w:bCs/><w:sz w:val="24"/><w:szCs w:val="24"/><w:u w:val="single"/></w:rPr></w:pPr><w:r w:rsidRPr="00DD6A89"><w:rPr><w:b/><w:bCs/><w:sz w:val="24"/><w:szCs w:val="24"/><w:u w:val="single"/></w:rPr><w:t>Call to Action</w:t></w:r></w:p><w:p w14:paraId="0CBD637C" w14:textId="44DC182E" w:rsidR="00DD6A89" w:rsidRPr="00B95E91" w:rsidRDefault="00DD6A89" w:rsidP="00DD6A89"><w:pPr><w:rPr><w:sz w:val="24"/><w:szCs w:val="24"/></w:rPr></w:pPr><w:r w:rsidRPr="00DD6A89"><w:rPr><w:sz w:val="24"/><w:szCs w:val="24"/></w:rPr><w:t>Ready to Grow Your Business?</w:t></w:r></w:p><w:p w14:paraId="5E507D20" w14:textId="462D7247" w:rsidR="00B95E91" w:rsidRDefault="00DD6A89" w:rsidP="00DD6A89"><w:pPr><w:ind w:firstLine="720"/></w:pPr><w:r w:rsidRPr="00DD6A89"><w:t xml:space="preserve">Let </w:t></w:r><w:proofErr w:type="spellStart"/><w:r w:rsidRPr="00DD6A89"><w:t>Flobitz</w:t></w:r><w:proofErr w:type="spellEnd"/><w:r w:rsidRPr="00DD6A89"><w:t xml:space="preserve"> help you achieve your goals with smart solutions.</w:t></w:r></w:p><w:p w14:paraId="1A090C8F" w14:textId="77777777" w:rsidR="00DD6A89" w:rsidRPr="00DD6A89" w:rsidRDefault="00DD6A89" w:rsidP="00DD6A89"><w:pPr><w:rPr><w:u w:val="single"/></w:rPr></w:pPr><w:r w:rsidRPr="00DD6A89"><w:rPr><w:b/><w:bCs/><w:u w:val="single"/></w:rPr><w:t>Button:</w:t></w:r></w:p><w:p w14:paraId="6833866A" w14:textId="77777777" w:rsidR="00DD6A89" w:rsidRPr="00DD6A89" w:rsidRDefault="00DD6A89" w:rsidP="00DD6A89"><w:pPr><w:numPr><w:ilvl w:val="0"/><w:numId w:val="3"/></w:numPr></w:pPr><w:r w:rsidRPr="00DD6A89"><w:t>Contact Us Today</w:t></w:r></w:p><w:p w14:paraId="0F09CF40" w14:textId="77777777" w:rsidR="00DD6A89" w:rsidRDefault="00DD6A89" w:rsidP="00DD6A89"/><w:p w14:paraId="576685DB" w14:textId="5F650A7E" w:rsidR="00DD6A89" w:rsidRPr="00DD6A89" w:rsidRDefault="00DD6A89" w:rsidP="00DD6A89"><w:r><w:tab/></w:r><w:r><w:tab/></w:r><w:r><w:tab/></w:r><w:r><w:tab/></w:r><w:r><w:tab/></w:r></w:p><w:sectPr w:rsidR="00DD6A89" w:rsidRPr="00DD6A89"><w:pgSz w:w="11906" w:h="16838"/><w:pgMar w:top="1440" w:right="1440" w:bottom="1440" w:left="1440" w:header="708" w:footer="708" w:gutter="0"/><w:cols w:space="708"/><w:docGrid w:linePitch="360"/></w:sectPr></w:body></w:document>